slap/__init__.py
slap/__main__.py
slap/application.py
slap/changelog.py
slap/check.py
slap/configuration.py
slap/ext/__init__.py
slap/ext/application/add.py
slap/ext/application/changelog.py
slap/ext/application/check.py
slap/ext/application/config.py
slap/ext/application/info.py
slap/ext/application/init.py
slap/ext/application/install.py
slap/ext/application/link.py
slap/ext/application/publish.py
slap/ext/application/release.py
slap/ext/application/report.py
slap/ext/application/run.py
slap/ext/application/test.py
slap/ext/application/venv.py
slap/ext/checks/__init__.py
slap/ext/checks/changelog.py
slap/ext/checks/general.py
slap/ext/checks/poetry.py
slap/ext/checks/release.py
slap/ext/project_handlers/base.py
slap/ext/project_handlers/flit.py
slap/ext/project_handlers/poetry.py
slap/ext/project_handlers/setuptools.py
slap/ext/project_handlers/uv.py
slap/ext/release/changelog.py
slap/ext/release/source_code_version.py
slap/ext/repository_ci/github_actions.py
slap/ext/repository_handlers/default.py
slap/ext/repository_hosts/github.py
slap/ext/version_incrementing_rule.py
slap/install/installer.py
slap/plugins.py
slap/project.py
slap/py.typed
slap/python/dependency.py
slap/python/environment.py
slap/python/pep508.py
slap/release.py
slap/repository.py
slap/templates/github/.github/workflows/changelog.yaml
slap/templates/github/.github/workflows/python.yaml
slap/templates/poetry/.flake8
slap/templates/poetry/.gitignore
slap/templates/poetry/LICENSE
slap/templates/poetry/README.md
slap/templates/poetry/pyproject.toml
slap/templates/poetry/src/{path}/__init__.py
slap/templates/poetry/src/{path}/py.typed
slap/templates/poetry/tests/test_import.py
slap/util/cleo.py
slap/util/digraph.py
slap/util/external/licenses.py
slap/util/external/pypi_classifiers.py
slap/util/fs.py
slap/util/git.py
slap/util/logging.py
slap/util/notset.py
slap/util/once.py
slap/util/orderedset.py
slap/util/plugins.py
slap/util/pygments.py
slap/util/strings.py
slap/util/supplier.py
slap_cli-1.15.0.dist-info/METADATA
slap_cli-1.15.0.dist-info/WHEEL
slap_cli-1.15.0.dist-info/entry_points.txt
slap_cli-1.15.0.dist-info/licenses/LICENSE
slap_cli-1.15.0.dist-info/RECORD
